pydoublelasso/__init__.py
pydoublelasso/double_post_lasso.py
pydoublelasso-0.2.0.dist-info/licenses/LICENSE
pydoublelasso-0.2.0.dist-info/METADATA
pydoublelasso-0.2.0.dist-info/WHEEL
pydoublelasso-0.2.0.dist-info/top_level.txt
pydoublelasso-0.2.0.dist-info/RECORD
